{
	"@metadata": {
		"authors": []
	},
	"ExtraOpenMissingClose": "Dodatne otkrыvaющuю braće ili dovoljno zatvaranja kovrdžavom brace",
	"ExtraCloseMissingOpen": "Dodatne zatvaranja kovrdžavom brace ili nedostaje otvorena braće zagrada",
	"MissingLeftExtraRight": "Nedostaje \\left ili ekstra \\right",
	"MissingScript": "Nedostaje natpis ili superskriptu argument",
	"ExtraLeftMissingRight": "Ekstra \\left ili nestalih \\right",
	"Misplaced": "Zagubljen $1",
	"MissingOpenForSub": "Nedostaje otvorena braće zagrada za podstročnogo",
	"MissingOpenForSup": "Nedostaje otvorena braće zagrada za natpis",
	"AmbiguousUseOf": "Dvosmislena upotreba $1",
	"EnvBadEnd": "\\begin{$1} završio \\end{$2}",
	"EnvMissingEnd": "Nedostaje \\end{$1}",
	"MissingBoxFor": "Nedostaje kutija za $1",
	"MissingCloseBrace": "Dovoljno zatvaranja kovrdžavom brace",
	"UndefinedControlSequence": "Neodređeni kontrole nizu $1",
	"DoubleExponent": "Dvostruki izlagači: koristite vitičaste zagrade za pojašnjenja",
	"DoubleSubscripts": "Duple donji indeksi: koristite vitičaste zagrade za pojašnjenja",
	"DoubleExponentPrime": "Premijer dovodi do dvostrukog эksponente: koristite vitičaste zagrade za pojašnjenja",
	"CantUseHash1": "Ne možete da koristite 'makro aspekt lika #' u matematičkom režimu",
	"MisplacedMiddle": "$1 mora biti u okviru \\left i \\right",
	"MisplacedLimits": "$1 dozvoljeno samo za operatere",
	"MisplacedMoveRoot": "$1 može da se pojavi samo u root",
	"MultipleCommand": "Više od $1",
	"IntegerArg": "Argument $1 mora biti ceo broj",
	"NotMathMLToken": "$1-To nije marker elementa",
	"InvalidMathMLAttr": "Neispravan atribut za MathML: $1",
	"UnknownAttrForElement": "$1 nije prepoznat kao atribut $2",
	"MaxMacroSub1": "Korišćenje MathJax maksimalna zamena makroa. dostižete broja; ovde rekurzivni poziv makroa?",
	"MaxMacroSub2": "Korišćenje MathJax maksimalnim supstitucija dostižete broja; da li postoji rekurzivne LaTeX sredine?",
	"MissingArgFor": "Nedostaje argument za $1"
}
