{
  "webFont": "This warning is displayed by the FontWarnings extension when web-based fonts are used.",
  "imageFonts": "This warning is displayed by the FontWarnings extension when image fonts are used.",
  "noFonts": "This warning is displayed by the FontWarnings extension when no fonts can be used.",
  "webFonts": "This warning is displayed by the FontWarnings extension when the browser do not support web fonts",
  "fonts": "This warning is displayed by the FontWarnings extension when the HTML-CSS availableFonts list contains both STIX and TeX",
  "STIXPage": "This warning is displayed by the FontWarnings extension when the HTML-CSS availableFonts list contains only STIX",
  "TeXPage": "This warning is displayed by the FontWarnings extension when the HTML-CSS availableFonts list contains only TeX"
}