{
    "@metadata": {
        "authors": [
            "Jopparn",
            "WikiPhoenix"
        ]
    },
    "MathMLcode": "MathML-kod",
    "OriginalMathML": "Ursprunglig MathML",
    "TeXCommands": "TeX-kommandon",
    "AsciiMathInput": "AsciiMathML-inmatning",
    "Original": "Ursprungligt format",
    "ErrorMessage": "Felmeddelande",
    "TeX": "TeX",
    "StarMath": "StarMath",
    "OpenMath": "OpenMath",
    "Click": "Klick",
    "DoubleClick": "Dubbelklick",
    "NoZoom": "Ingen zoom",
    "Option": "Alternativ",
    "Alt": "Alt",
    "Command": "Command",
    "Control": "Ctrl",
    "Shift": "Shift",
    "MenuEvents": "Menyhändelser",
    "MouseEvents": "Mushändelser",
    "MenuAndMouse": "Mus- och menyhändelser",
    "FontPrefs": "Teckensnittsinställningar",
    "ForHTMLCSS": "För HTML-CSS:",
    "TeXLocal": "TeX (lokal)",
    "TeXWeb": "TeX (webb)",
    "TeXImage": "TeX (bild)",
    "STIXLocal": "STIX (lokal)",
    "Locale": "Språk",
    "LoadLocale": "Läs in från URL ...",
    "About": "Om MathJax",
    "Help": "Hjälp för MathJax",
    "eotffonts": "eot-teckensnitt",
    "svgfonts": "svg-teckensnitt",
    "Close": "Stäng"
}